Metadata-Version: 1.0
Name: distributions-jesus
Version: 0.1
Summary: Gaussian distributions
Home-page: UNKNOWN
Author: Jesus Mira
Author-email: jesus.mira1@hotmail.com
License: UNKNOWN
Platform: UNKNOWN
